{
    "configurations": [
        {
            "name": "Win32",
            "includePath": [
                "C:\\Users\\david\\OneDrive\\Documents\\Arduino\\libraries\\Adafruit_Unified_Sensor",
                "C:\\Users\\david\\AppData\\Local\\Arduino15\\packages\\arduino\\tools\\**",
                "C:\\Users\\david\\OneDrive\\Documents\\Arduino\\libraries\\**",
                "C:\\Program Files (x86)\\Arduino\\libraries\\**",
                "C:\\Users\\david\\AppData\\Local\\Arduino15\\packages\\arduino\\hardware\\samd\\1.8.11\\**",
                "${workspaceFolder}/**",
                "${workspaceFolder}",
                "${workspaceRoot}",
                "C:\\dev\\rocketcontrol"
            ],
            "defines": [
                "_DEBUG",
                "UNICODE",
                "_UNICODE",
                "USBCON"
            ],
            "cStandard": "c17",
            "cppStandard": "c++17",
            "intelliSenseMode": "windows-msvc-x64",
            "forcedInclude": [
                "C:\\Users\\david\\AppData\\Local\\Arduino15\\packages\\arduino\\hardware\\samd\\1.8.11\\cores\\arduino\\Arduino.h"
            ]
        }
    ],
    "version": 4
}